admin_interface/__init__.py
admin_interface/admin.py
admin_interface/apps.py
admin_interface/cache.py
admin_interface/compat.py
admin_interface/models.py
admin_interface/settings.py
admin_interface/version.py
admin_interface/fixtures/admin_interface_theme_uswds.json
admin_interface/locale/es/LC_MESSAGES/django.mo
admin_interface/locale/es/LC_MESSAGES/django.po
admin_interface/locale/fa/LC_MESSAGES/django.mo
admin_interface/locale/fa/LC_MESSAGES/django.po
admin_interface/locale/fr/LC_MESSAGES/django.mo
admin_interface/locale/fr/LC_MESSAGES/django.po
admin_interface/locale/it/LC_MESSAGES/django.mo
admin_interface/locale/it/LC_MESSAGES/django.po
admin_interface/locale/tr/LC_MESSAGES/django.mo
admin_interface/locale/tr/LC_MESSAGES/django.po
admin_interface/migrations/0001_initial.py
admin_interface/migrations/__init__.py
admin_interface/static/admin/css/base.css
admin_interface/static/admin/css/changelists.css
admin_interface/static/admin/css/nav_sidebar.css
admin_interface/static/admin/js/actions.js
admin_interface/static/admin/js/cancel.js
admin_interface/static/admin/js/nav_sidebar.js
admin_interface/static/admin/js/popup_response.js
admin_interface/static/admin_interface/508/actions.js
admin_interface/static/admin_interface/508/dropdown-filter.js
admin_interface/static/admin_interface/508/error-alert.js
admin_interface/static/admin_interface/508/form-labels.js
admin_interface/static/admin_interface/508/help-tooltip.js
admin_interface/static/admin_interface/508/required-field-error.js
admin_interface/static/admin_interface/508/table-checkboxes.js
admin_interface/static/admin_interface/favico/favico-0.3.10-patched.js
admin_interface/static/admin_interface/favico/favico-0.3.10-patched.min.js
admin_interface/static/admin_interface/magnific-popup/jquery.magnific-popup.js
admin_interface/static/admin_interface/magnific-popup/magnific-popup.css
admin_interface/static/admin_interface/related-modal/related-modal.js
django_admin_508-1.0.3.dist-info/licenses/LICENSE.txt
django_admin_508-1.0.3.dist-info/METADATA
django_admin_508-1.0.3.dist-info/WHEEL
django_admin_508-1.0.3.dist-info/top_level.txt
django_admin_508-1.0.3.dist-info/RECORD
