Metadata-Version: 2.4
Name: django-admin-508
Version: 1.0.3
Summary: django-admin-508 is a modern responsive django admin interface.
Home-page: https://github.com/raft-tech/django-admin-508
Download-URL: https://github.com/raft-tech/django-admin-508/archive/1.0.3.tar.gz
Author: Raft
Author-email: info@goraft.tech
License: MIT
Keywords: django,admin,interface,responsive,flat,theme,custom,ui
Classifier: Development Status :: 5 - Production/Stable
Classifier: Environment :: Web Environment
Classifier: Framework :: Django
Classifier: Framework :: Django :: 1.7
Classifier: Framework :: Django :: 1.8
Classifier: Framework :: Django :: 1.9
Classifier: Framework :: Django :: 1.10
Classifier: Framework :: Django :: 1.11
Classifier: Framework :: Django :: 2.0
Classifier: Framework :: Django :: 2.1
Classifier: Framework :: Django :: 2.2
Classifier: Framework :: Django :: 3.0
Classifier: Framework :: Django :: 3.1
Classifier: Framework :: Django :: 3.2
Classifier: Intended Audience :: Developers
Classifier: License :: OSI Approved :: MIT License
Classifier: Natural Language :: English
Classifier: Operating System :: OS Independent
Classifier: Programming Language :: Python :: 2
Classifier: Programming Language :: Python :: 2.7
Classifier: Programming Language :: Python :: 3
Classifier: Programming Language :: Python :: 3.4
Classifier: Programming Language :: Python :: 3.5
Classifier: Programming Language :: Python :: 3.6
Classifier: Programming Language :: Python :: 3.7
Classifier: Programming Language :: Python :: 3.8
Classifier: Programming Language :: Python :: 3.9
Classifier: Topic :: Software Development :: Build Tools
Requires: django(>=1.7)
License-File: LICENSE.txt
Requires-Dist: django-colorfield<1.0,>=0.2
Requires-Dist: django-flat-theme<2.0,>=1.0
Requires-Dist: django-flat-responsive<3.0,>=1.0
Requires-Dist: six<2.0.0,>=1.9.0
Dynamic: author
Dynamic: author-email
Dynamic: classifier
Dynamic: description
Dynamic: description-content-type
Dynamic: download-url
Dynamic: home-page
Dynamic: keywords
Dynamic: license
Dynamic: license-file
Dynamic: requires
Dynamic: requires-dist
Dynamic: summary
